{
  "annotated": false,
  "annotation": [
    {
      "class": "Nyctalus leisleri",
      "class_prob": 0.267,
      "det_prob": 0.66,
      "end_time": 0.1206,
      "event": "Echolocation",
      "high_freq": 43488,
      "individual": "-1",
      "low_freq": 34921,
      "start_time": 0.1125
    },
    {
      "class": "Nyctalus leisleri",
      "class_prob": 0.237,
      "det_prob": 0.681,
      "end_time": 0.3493,
      "event": "Echolocation",
      "high_freq": 42372,
      "individual": "-1",
      "low_freq": 34062,
      "start_time": 0.3415
    },
    {
      "class": "Eptesicus serotinus",
      "class_prob": 0.309,
      "det_prob": 0.67,
      "end_time": 0.4592,
      "event": "Echolocation",
      "high_freq": 43517,
      "individual": "-1",
      "low_freq": 34062,
      "start_time": 0.4515
    },
    {
      "class": "Eptesicus serotinus",
      "class_prob": 0.323,
      "det_prob": 0.639,
      "end_time": 0.7035,
      "event": "Echolocation",
      "high_freq": 45361,
      "individual": "-1",
      "low_freq": 34062,
      "start_time": 0.6965
    },
    {
      "class": "Eptesicus serotinus",
      "class_prob": 0.368,
      "det_prob": 0.766,
      "end_time": 0.8323,
      "event": "Echolocation",
      "high_freq": 47509,
      "individual": "-1",
      "low_freq": 34062,
      "start_time": 0.8235
    },
    {
      "class": "Eptesicus serotinus",
      "class_prob": 0.36,
      "det_prob": 0.77,
      "end_time": 0.9501,
      "event": "Echolocation",
      "high_freq": 45070,
      "individual": "-1",
      "low_freq": 34062,
      "start_time": 0.9425
    },
    {
      "class": "Nyctalus leisleri",
      "class_prob": 0.346,
      "det_prob": 0.76,
      "end_time": 1.2968,
      "event": "Echolocation",
      "high_freq": 44483,
      "individual": "-1",
      "low_freq": 34062,
      "start_time": 1.2885
    },
    {
      "class": "Eptesicus serotinus",
      "class_prob": 0.338,
      "det_prob": 0.74,
      "end_time": 1.4363,
      "event": "Echolocation",
      "high_freq": 47892,
      "individual": "-1",
      "low_freq": 33203,
      "start_time": 1.4255
    },
    {
      "class": "Nyctalus leisleri",
      "class_prob": 0.331,
      "det_prob": 0.789,
      "end_time": 1.6928,
      "event": "Echolocation",
      "high_freq": 47205,
      "individual": "-1",
      "low_freq": 34062,
      "start_time": 1.6845
    },
    {
      "class": "Eptesicus serotinus",
      "class_prob": 0.426,
      "det_prob": 0.724,
      "end_time": 2.0645,
      "event": "Echolocation",
      "high_freq": 47658,
      "individual": "-1",
      "low_freq": 34062,
      "start_time": 2.0555
    },
    {
      "class": "Eptesicus serotinus",
      "class_prob": 0.428,
      "det_prob": 0.672,
      "end_time": 2.1902,
      "event": "Echolocation",
      "high_freq": 45460,
      "individual": "-1",
      "low_freq": 33203,
      "start_time": 2.1785
    },
    {
      "class": "Eptesicus serotinus",
      "class_prob": 0.359,
      "det_prob": 0.719,
      "end_time": 2.428,
      "event": "Echolocation",
      "high_freq": 50896,
      "individual": "-1",
      "low_freq": 34062,
      "start_time": 2.4175
    },
    {
      "class": "Eptesicus serotinus",
      "class_prob": 0.317,
      "det_prob": 0.688,
      "end_time": 2.7919,
      "event": "Echolocation",
      "high_freq": 46636,
      "individual": "-1",
      "low_freq": 34062,
      "start_time": 2.7825
    },
    {
      "class": "Eptesicus serotinus",
      "class_prob": 0.268,
      "det_prob": 0.578,
      "end_time": 2.9178,
      "event": "Echolocation",
      "high_freq": 45505,
      "individual": "-1",
      "low_freq": 33203,
      "start_time": 2.9065
    },
    {
      "class": "Eptesicus serotinus",
      "class_prob": 0.553,
      "det_prob": 0.747,
      "end_time": 3.2857,
      "event": "Echolocation",
      "high_freq": 53210,
      "individual": "-1",
      "low_freq": 32343,
      "start_time": 3.2735
    },
    {
      "class": "Eptesicus serotinus",
      "class_prob": 0.578,
      "det_prob": 0.712,
      "end_time": 3.4125,
      "event": "Echolocation",
      "high_freq": 47750,
      "individual": "-1",
      "low_freq": 32343,
      "start_time": 3.3995
    },
    {
      "class": "Pipistrellus nathusii",
      "class_prob": 0.411,
      "det_prob": 0.65,
      "end_time": 3.7639,
      "event": "Echolocation",
      "high_freq": 54930,
      "individual": "-1",
      "low_freq": 33203,
      "start_time": 3.7535
    },
    {
      "class": "Eptesicus serotinus",
      "class_prob": 0.463,
      "det_prob": 0.647,
      "end_time": 3.8921,
      "event": "Echolocation",
      "high_freq": 49087,
      "individual": "-1",
      "low_freq": 32343,
      "start_time": 3.8805
    },
    {
      "class": "Pipistrellus nathusii",
      "class_prob": 0.217,
      "det_prob": 0.429,
      "end_time": 4.1267,
      "event": "Echolocation",
      "high_freq": 59225,
      "individual": "-1",
      "low_freq": 33203,
      "start_time": 4.1185
    },
    {
      "class": "Eptesicus serotinus",
      "class_prob": 0.367,
      "det_prob": 0.48,
      "end_time": 4.3665,
      "event": "Echolocation",
      "high_freq": 53095,
      "individual": "-1",
      "low_freq": 31484,
      "start_time": 4.3575
    },
    {
      "class": "Pipistrellus nathusii",
      "class_prob": 0.166,
      "det_prob": 0.403,
      "end_time": 4.4931,
      "event": "Echolocation",
      "high_freq": 60509,
      "individual": "-1",
      "low_freq": 33203,
      "start_time": 4.4845
    },
    {
      "class": "Eptesicus serotinus",
      "class_prob": 0.204,
      "det_prob": 0.409,
      "end_time": 4.742,
      "event": "Echolocation",
      "high_freq": 61692,
      "individual": "-1",
      "low_freq": 32343,
      "start_time": 4.7345
    },
    {
      "class": "Eptesicus serotinus",
      "class_prob": 0.489,
      "det_prob": 0.606,
      "end_time": 4.8618,
      "event": "Echolocation",
      "high_freq": 53168,
      "individual": "-1",
      "low_freq": 28906,
      "start_time": 4.8545
    },
    {
      "class": "Eptesicus serotinus",
      "class_prob": 0.345,
      "det_prob": 0.511,
      "end_time": 4.9832,
      "event": "Echolocation",
      "high_freq": 62443,
      "individual": "-1",
      "low_freq": 32343,
      "start_time": 4.9755
    },
    {
      "class": "Eptesicus serotinus",
      "class_prob": 0.56,
      "det_prob": 0.671,
      "end_time": 5.1073,
      "event": "Echolocation",
      "high_freq": 53156,
      "individual": "-1",
      "low_freq": 30625,
      "start_time": 5.0995
    },
    {
      "class": "Eptesicus serotinus",
      "class_prob": 0.343,
      "det_prob": 0.507,
      "end_time": 5.223,
      "event": "Echolocation",
      "high_freq": 59517,
      "individual": "-1",
      "low_freq": 32343,
      "start_time": 5.2155
    },
    {
      "class": "Eptesicus serotinus",
      "class_prob": 0.567,
      "det_prob": 0.686,
      "end_time": 5.3436,
      "event": "Echolocation",
      "high_freq": 51286,
      "individual": "-1",
      "low_freq": 31484,
      "start_time": 5.3355
    },
    {
      "class": "Eptesicus serotinus",
      "class_prob": 0.519,
      "det_prob": 0.659,
      "end_time": 5.4229,
      "event": "Echolocation",
      "high_freq": 53638,
      "individual": "-1",
      "low_freq": 31484,
      "start_time": 5.4155
    },
    {
      "class": "Eptesicus serotinus",
      "class_prob": 0.396,
      "det_prob": 0.502,
      "end_time": 5.565,
      "event": "Echolocation",
      "high_freq": 58679,
      "individual": "-1",
      "low_freq": 30625,
      "start_time": 5.5585
    },
    {
      "class": "Eptesicus serotinus",
      "class_prob": 0.472,
      "det_prob": 0.573,
      "end_time": 5.6921,
      "event": "Echolocation",
      "high_freq": 52345,
      "individual": "-1",
      "low_freq": 32343,
      "start_time": 5.6845
    },
    {
      "class": "Eptesicus serotinus",
      "class_prob": 0.426,
      "det_prob": 0.557,
      "end_time": 5.8004,
      "event": "Echolocation",
      "high_freq": 58238,
      "individual": "-1",
      "low_freq": 31484,
      "start_time": 5.7935
    },
    {
      "class": "Eptesicus serotinus",
      "class_prob": 0.415,
      "det_prob": 0.532,
      "end_time": 5.9176,
      "event": "Echolocation",
      "high_freq": 48220,
      "individual": "-1",
      "low_freq": 32343,
      "start_time": 5.9125
    },
    {
      "class": "Eptesicus serotinus",
      "class_prob": 0.57,
      "det_prob": 0.646,
      "end_time": 6.0334,
      "event": "Echolocation",
      "high_freq": 53347,
      "individual": "-1",
      "low_freq": 31484,
      "start_time": 6.0265
    },
    {
      "class": "Eptesicus serotinus",
      "class_prob": 0.399,
      "det_prob": 0.5,
      "end_time": 6.1458,
      "event": "Echolocation",
      "high_freq": 43279,
      "individual": "-1",
      "low_freq": 32343,
      "start_time": 6.1385
    },
    {
      "class": "Eptesicus serotinus",
      "class_prob": 0.528,
      "det_prob": 0.624,
      "end_time": 6.2531,
      "event": "Echolocation",
      "high_freq": 45797,
      "individual": "-1",
      "low_freq": 31484,
      "start_time": 6.2475
    },
    {
      "class": "Eptesicus serotinus",
      "class_prob": 0.512,
      "det_prob": 0.617,
      "end_time": 6.3595,
      "event": "Echolocation",
      "high_freq": 46871,
      "individual": "-1",
      "low_freq": 32343,
      "start_time": 6.3545
    },
    {
      "class": "Eptesicus serotinus",
      "class_prob": 0.478,
      "det_prob": 0.583,
      "end_time": 6.4108,
      "event": "Echolocation",
      "high_freq": 47477,
      "individual": "-1",
      "low_freq": 32343,
      "start_time": 6.4055
    },
    {
      "class": "Eptesicus serotinus",
      "class_prob": 0.566,
      "det_prob": 0.657,
      "end_time": 6.4544,
      "event": "Echolocation",
      "high_freq": 46486,
      "individual": "-1",
      "low_freq": 30625,
      "start_time": 6.4485
    },
    {
      "class": "Eptesicus serotinus",
      "class_prob": 0.523,
      "det_prob": 0.645,
      "end_time": 6.5625,
      "event": "Echolocation",
      "high_freq": 46334,
      "individual": "-1",
      "low_freq": 33203,
      "start_time": 6.5575
    },
    {
      "class": "Eptesicus serotinus",
      "class_prob": 0.579,
      "det_prob": 0.666,
      "end_time": 6.6677,
      "event": "Echolocation",
      "high_freq": 48975,
      "individual": "-1",
      "low_freq": 32343,
      "start_time": 6.6615
    },
    {
      "class": "Eptesicus serotinus",
      "class_prob": 0.504,
      "det_prob": 0.599,
      "end_time": 6.7857,
      "event": "Echolocation",
      "high_freq": 45838,
      "individual": "-1",
      "low_freq": 32343,
      "start_time": 6.7795
    },
    {
      "class": "Eptesicus serotinus",
      "class_prob": 0.547,
      "det_prob": 0.636,
      "end_time": 6.924,
      "event": "Echolocation",
      "high_freq": 47408,
      "individual": "-1",
      "low_freq": 33203,
      "start_time": 6.9175
    },
    {
      "class": "Eptesicus serotinus",
      "class_prob": 0.509,
      "det_prob": 0.648,
      "end_time": 7.0243,
      "event": "Echolocation",
      "high_freq": 45990,
      "individual": "-1",
      "low_freq": 33203,
      "start_time": 7.0185
    },
    {
      "class": "Eptesicus serotinus",
      "class_prob": 0.394,
      "det_prob": 0.492,
      "end_time": 7.1537,
      "event": "Echolocation",
      "high_freq": 43819,
      "individual": "-1",
      "low_freq": 33203,
      "start_time": 7.1455
    },
    {
      "class": "Eptesicus serotinus",
      "class_prob": 0.44,
      "det_prob": 0.623,
      "end_time": 7.2768,
      "event": "Echolocation",
      "high_freq": 45086,
      "individual": "-1",
      "low_freq": 33203,
      "start_time": 7.2695
    },
    {
      "class": "Eptesicus serotinus",
      "class_prob": 0.328,
      "det_prob": 0.537,
      "end_time": 7.5428,
      "event": "Echolocation",
      "high_freq": 42279,
      "individual": "-1",
      "low_freq": 34062,
      "start_time": 7.5345
    },
    {
      "class": "Eptesicus serotinus",
      "class_prob": 0.349,
      "det_prob": 0.584,
      "end_time": 7.79,
      "event": "Echolocation",
      "high_freq": 43262,
      "individual": "-1",
      "low_freq": 34062,
      "start_time": 7.7825
    },
    {
      "class": "Pipistrellus nathusii",
      "class_prob": 0.291,
      "det_prob": 0.722,
      "end_time": 8.0237,
      "event": "Echolocation",
      "high_freq": 42453,
      "individual": "-1",
      "low_freq": 33203,
      "start_time": 8.0155
    },
    {
      "class": "Nyctalus leisleri",
      "class_prob": 0.262,
      "det_prob": 0.759,
      "end_time": 8.1505,
      "event": "Echolocation",
      "high_freq": 43063,
      "individual": "-1",
      "low_freq": 34062,
      "start_time": 8.1425
    },
    {
      "class": "Pipistrellus nathusii",
      "class_prob": 0.27,
      "det_prob": 0.711,
      "end_time": 8.3957,
      "event": "Echolocation",
      "high_freq": 40538,
      "individual": "-1",
      "low_freq": 34062,
      "start_time": 8.3865
    }
  ],
  "class_name": "Eptesicus serotinus",
  "duration": 10.2747,
  "id": "NYMND-PLTG_20241023_170621.wav",
  "issues": false,
  "notes": "Automatically generated.",
  "time_exp": 1
}