{
  "annotated": false,
  "annotation": [
    {
      "class": "Myotis daubentonii",
      "class_prob": 0.322,
      "det_prob": 0.411,
      "end_time": 0.1052,
      "event": "Echolocation",
      "high_freq": 57270,
      "individual": "-1",
      "low_freq": 41796,
      "start_time": 0.1005
    },
    {
      "class": "Myotis daubentonii",
      "class_prob": 0.43,
      "det_prob": 0.506,
      "end_time": 0.1731,
      "event": "Echolocation",
      "high_freq": 58139,
      "individual": "-1",
      "low_freq": 39218,
      "start_time": 0.1685
    },
    {
      "class": "Myotis daubentonii",
      "class_prob": 0.439,
      "det_prob": 0.622,
      "end_time": 0.3083,
      "event": "Echolocation",
      "high_freq": 56852,
      "individual": "-1",
      "low_freq": 40937,
      "start_time": 0.3035
    },
    {
      "class": "Myotis daubentonii",
      "class_prob": 0.37,
      "det_prob": 0.494,
      "end_time": 0.3516,
      "event": "Echolocation",
      "high_freq": 57949,
      "individual": "-1",
      "low_freq": 38359,
      "start_time": 0.3475
    },
    {
      "class": "Myotis daubentonii",
      "class_prob": 0.426,
      "det_prob": 0.584,
      "end_time": 0.4137,
      "event": "Echolocation",
      "high_freq": 62689,
      "individual": "-1",
      "low_freq": 41796,
      "start_time": 0.4085
    },
    {
      "class": "Myotis daubentonii",
      "class_prob": 0.429,
      "det_prob": 0.548,
      "end_time": 0.5128,
      "event": "Echolocation",
      "high_freq": 57175,
      "individual": "-1",
      "low_freq": 41796,
      "start_time": 0.5075
    },
    {
      "class": "Myotis daubentonii",
      "class_prob": 0.428,
      "det_prob": 0.491,
      "end_time": 0.5397,
      "event": "Echolocation",
      "high_freq": 56070,
      "individual": "-1",
      "low_freq": 34921,
      "start_time": 0.5355
    },
    {
      "class": "Myotis daubentonii",
      "class_prob": 0.424,
      "det_prob": 0.497,
      "end_time": 0.6178,
      "event": "Echolocation",
      "high_freq": 57238,
      "individual": "-1",
      "low_freq": 40937,
      "start_time": 0.6135
    },
    {
      "class": "Myotis daubentonii",
      "class_prob": 0.362,
      "det_prob": 0.437,
      "end_time": 0.6306,
      "event": "Echolocation",
      "high_freq": 54058,
      "individual": "-1",
      "low_freq": 40937,
      "start_time": 0.6265
    },
    {
      "class": "Myotis daubentonii",
      "class_prob": 0.363,
      "det_prob": 0.547,
      "end_time": 0.7177,
      "event": "Echolocation",
      "high_freq": 59372,
      "individual": "-1",
      "low_freq": 43515,
      "start_time": 0.7125
    },
    {
      "class": "Myotis daubentonii",
      "class_prob": 0.484,
      "det_prob": 0.559,
      "end_time": 0.82,
      "event": "Echolocation",
      "high_freq": 62118,
      "individual": "-1",
      "low_freq": 41796,
      "start_time": 0.8145
    },
    {
      "class": "Myotis daubentonii",
      "class_prob": 0.406,
      "det_prob": 0.59,
      "end_time": 0.9217,
      "event": "Echolocation",
      "high_freq": 59781,
      "individual": "-1",
      "low_freq": 41796,
      "start_time": 0.9165
    },
    {
      "class": "Myotis daubentonii",
      "class_prob": 0.415,
      "det_prob": 0.5,
      "end_time": 0.9891,
      "event": "Echolocation",
      "high_freq": 56376,
      "individual": "-1",
      "low_freq": 41796,
      "start_time": 0.9845
    },
    {
      "class": "Myotis daubentonii",
      "class_prob": 0.445,
      "det_prob": 0.549,
      "end_time": 1.0255,
      "event": "Echolocation",
      "high_freq": 55983,
      "individual": "-1",
      "low_freq": 40078,
      "start_time": 1.0205
    },
    {
      "class": "Myotis daubentonii",
      "class_prob": 0.463,
      "det_prob": 0.594,
      "end_time": 1.1287,
      "event": "Echolocation",
      "high_freq": 59542,
      "individual": "-1",
      "low_freq": 41796,
      "start_time": 1.1235
    },
    {
      "class": "Myotis daubentonii",
      "class_prob": 0.324,
      "det_prob": 0.436,
      "end_time": 1.1722,
      "event": "Echolocation",
      "high_freq": 56134,
      "individual": "-1",
      "low_freq": 37500,
      "start_time": 1.1685
    },
    {
      "class": "Pipistrellus pipistrellus",
      "class_prob": 0.477,
      "det_prob": 0.518,
      "end_time": 1.2247,
      "event": "Echolocation",
      "high_freq": 58564,
      "individual": "-1",
      "low_freq": 46093,
      "start_time": 1.2195
    },
    {
      "class": "Myotis daubentonii",
      "class_prob": 0.463,
      "det_prob": 0.663,
      "end_time": 1.327,
      "event": "Echolocation",
      "high_freq": 61713,
      "individual": "-1",
      "low_freq": 41796,
      "start_time": 1.3215
    },
    {
      "class": "Myotis daubentonii",
      "class_prob": 0.379,
      "det_prob": 0.557,
      "end_time": 1.4234,
      "event": "Echolocation",
      "high_freq": 63104,
      "individual": "-1",
      "low_freq": 40078,
      "start_time": 1.4185
    },
    {
      "class": "Myotis daubentonii",
      "class_prob": 0.364,
      "det_prob": 0.435,
      "end_time": 1.4823,
      "event": "Echolocation",
      "high_freq": 57997,
      "individual": "-1",
      "low_freq": 37500,
      "start_time": 1.4785
    },
    {
      "class": "Myotis daubentonii",
      "class_prob": 0.41,
      "det_prob": 0.547,
      "end_time": 1.5244,
      "event": "Echolocation",
      "high_freq": 69529,
      "individual": "-1",
      "low_freq": 38359,
      "start_time": 1.5195
    },
    {
      "class": "Myotis daubentonii",
      "class_prob": 0.467,
      "det_prob": 0.527,
      "end_time": 1.5413,
      "event": "Echolocation",
      "high_freq": 55676,
      "individual": "-1",
      "low_freq": 34921,
      "start_time": 1.5375
    },
    {
      "class": "Myotis daubentonii",
      "class_prob": 0.435,
      "det_prob": 0.617,
      "end_time": 1.6236,
      "event": "Echolocation",
      "high_freq": 67869,
      "individual": "-1",
      "low_freq": 39218,
      "start_time": 1.6185
    },
    {
      "class": "Myotis daubentonii",
      "class_prob": 0.442,
      "det_prob": 0.525,
      "end_time": 1.7066,
      "event": "Echolocation",
      "high_freq": 56652,
      "individual": "-1",
      "low_freq": 35781,
      "start_time": 1.7025
    },
    {
      "class": "Myotis daubentonii",
      "class_prob": 0.408,
      "det_prob": 0.58,
      "end_time": 1.722,
      "event": "Echolocation",
      "high_freq": 68922,
      "individual": "-1",
      "low_freq": 40937,
      "start_time": 1.7165
    },
    {
      "class": "Myotis daubentonii",
      "class_prob": 0.499,
      "det_prob": 0.596,
      "end_time": 1.7975,
      "event": "Echolocation",
      "high_freq": 60098,
      "individual": "-1",
      "low_freq": 33203,
      "start_time": 1.7925
    },
    {
      "class": "Myotis daubentonii",
      "class_prob": 0.412,
      "det_prob": 0.561,
      "end_time": 1.8192,
      "event": "Echolocation",
      "high_freq": 68126,
      "individual": "-1",
      "low_freq": 39218,
      "start_time": 1.8135
    },
    {
      "class": "Myotis daubentonii",
      "class_prob": 0.43,
      "det_prob": 0.583,
      "end_time": 1.9182,
      "event": "Echolocation",
      "high_freq": 69730,
      "individual": "-1",
      "low_freq": 39218,
      "start_time": 1.9125
    },
    {
      "class": "Myotis daubentonii",
      "class_prob": 0.43,
      "det_prob": 0.526,
      "end_time": 1.9385,
      "event": "Echolocation",
      "high_freq": 63934,
      "individual": "-1",
      "low_freq": 33203,
      "start_time": 1.9345
    },
    {
      "class": "Myotis daubentonii",
      "class_prob": 0.455,
      "det_prob": 0.577,
      "end_time": 1.9881,
      "event": "Echolocation",
      "high_freq": 64833,
      "individual": "-1",
      "low_freq": 34921,
      "start_time": 1.9835
    },
    {
      "class": "Myotis daubentonii",
      "class_prob": 0.487,
      "det_prob": 0.61,
      "end_time": 2.0185,
      "event": "Echolocation",
      "high_freq": 65078,
      "individual": "-1",
      "low_freq": 40937,
      "start_time": 2.0125
    },
    {
      "class": "Myotis daubentonii",
      "class_prob": 0.333,
      "det_prob": 0.495,
      "end_time": 2.069,
      "event": "Echolocation",
      "high_freq": 61185,
      "individual": "-1",
      "low_freq": 34062,
      "start_time": 2.0655
    },
    {
      "class": "Myotis daubentonii",
      "class_prob": 0.424,
      "det_prob": 0.539,
      "end_time": 2.1221,
      "event": "Echolocation",
      "high_freq": 69973,
      "individual": "-1",
      "low_freq": 37500,
      "start_time": 2.1165
    },
    {
      "class": "Myotis daubentonii",
      "class_prob": 0.413,
      "det_prob": 0.578,
      "end_time": 2.162,
      "event": "Echolocation",
      "high_freq": 65074,
      "individual": "-1",
      "low_freq": 34062,
      "start_time": 2.1575
    },
    {
      "class": "Myotis daubentonii",
      "class_prob": 0.392,
      "det_prob": 0.547,
      "end_time": 2.2191,
      "event": "Echolocation",
      "high_freq": 70888,
      "individual": "-1",
      "low_freq": 38359,
      "start_time": 2.2135
    },
    {
      "class": "Myotis daubentonii",
      "class_prob": 0.348,
      "det_prob": 0.462,
      "end_time": 2.3194,
      "event": "Echolocation",
      "high_freq": 66941,
      "individual": "-1",
      "low_freq": 38359,
      "start_time": 2.3145
    },
    {
      "class": "Myotis daubentonii",
      "class_prob": 0.259,
      "det_prob": 0.461,
      "end_time": 2.3284,
      "event": "Echolocation",
      "high_freq": 64546,
      "individual": "-1",
      "low_freq": 34921,
      "start_time": 2.3245
    },
    {
      "class": "Myotis daubentonii",
      "class_prob": 0.34,
      "det_prob": 0.465,
      "end_time": 2.4165,
      "event": "Echolocation",
      "high_freq": 68103,
      "individual": "-1",
      "low_freq": 36640,
      "start_time": 2.4115
    },
    {
      "class": "Myotis daubentonii",
      "class_prob": 0.199,
      "det_prob": 0.498,
      "end_time": 2.4235,
      "event": "Echolocation",
      "high_freq": 66435,
      "individual": "-1",
      "low_freq": 36640,
      "start_time": 2.4195
    },
    {
      "class": "Myotis daubentonii",
      "class_prob": 0.477,
      "det_prob": 0.593,
      "end_time": 2.5148,
      "event": "Echolocation",
      "high_freq": 68336,
      "individual": "-1",
      "low_freq": 40078,
      "start_time": 2.5095
    },
    {
      "class": "Myotis daubentonii",
      "class_prob": 0.628,
      "det_prob": 0.705,
      "end_time": 2.5635,
      "event": "Echolocation",
      "high_freq": 67382,
      "individual": "-1",
      "low_freq": 30625,
      "start_time": 2.5585
    },
    {
      "class": "Myotis daubentonii",
      "class_prob": 0.332,
      "det_prob": 0.47,
      "end_time": 2.6036,
      "event": "Echolocation",
      "high_freq": 73694,
      "individual": "-1",
      "low_freq": 40078,
      "start_time": 2.5985
    },
    {
      "class": "Myotis daubentonii",
      "class_prob": 0.438,
      "det_prob": 0.539,
      "end_time": 2.6169,
      "event": "Echolocation",
      "high_freq": 62768,
      "individual": "-1",
      "low_freq": 33203,
      "start_time": 2.6125
    },
    {
      "class": "Myotis daubentonii",
      "class_prob": 0.434,
      "det_prob": 0.584,
      "end_time": 2.694,
      "event": "Echolocation",
      "high_freq": 69749,
      "individual": "-1",
      "low_freq": 33203,
      "start_time": 2.6885
    },
    {
      "class": "Myotis daubentonii",
      "class_prob": 0.393,
      "det_prob": 0.513,
      "end_time": 2.7094,
      "event": "Echolocation",
      "high_freq": 62102,
      "individual": "-1",
      "low_freq": 40078,
      "start_time": 2.7045
    },
    {
      "class": "Myotis daubentonii",
      "class_prob": 0.396,
      "det_prob": 0.573,
      "end_time": 2.8064,
      "event": "Echolocation",
      "high_freq": 61271,
      "individual": "-1",
      "low_freq": 44375,
      "start_time": 2.8015
    },
    {
      "class": "Myotis daubentonii",
      "class_prob": 0.496,
      "det_prob": 0.621,
      "end_time": 2.8635,
      "event": "Echolocation",
      "high_freq": 68092,
      "individual": "-1",
      "low_freq": 32343,
      "start_time": 2.8585
    },
    {
      "class": "Myotis daubentonii",
      "class_prob": 0.491,
      "det_prob": 0.624,
      "end_time": 2.9063,
      "event": "Echolocation",
      "high_freq": 70247,
      "individual": "-1",
      "low_freq": 41796,
      "start_time": 2.9005
    },
    {
      "class": "Myotis daubentonii",
      "class_prob": 0.527,
      "det_prob": 0.589,
      "end_time": 3.0057,
      "event": "Echolocation",
      "high_freq": 67268,
      "individual": "-1",
      "low_freq": 40937,
      "start_time": 2.9995
    },
    {
      "class": "Myotis daubentonii",
      "class_prob": 0.396,
      "det_prob": 0.555,
      "end_time": 3.0417,
      "event": "Echolocation",
      "high_freq": 63126,
      "individual": "-1",
      "low_freq": 36640,
      "start_time": 3.0375
    },
    {
      "class": "Myotis daubentonii",
      "class_prob": 0.576,
      "det_prob": 0.641,
      "end_time": 3.1097,
      "event": "Echolocation",
      "high_freq": 57530,
      "individual": "-1",
      "low_freq": 40937,
      "start_time": 3.1045
    },
    {
      "class": "Myotis daubentonii",
      "class_prob": 0.443,
      "det_prob": 0.608,
      "end_time": 3.1354,
      "event": "Echolocation",
      "high_freq": 57610,
      "individual": "-1",
      "low_freq": 40078,
      "start_time": 3.1315
    },
    {
      "class": "Myotis daubentonii",
      "class_prob": 0.442,
      "det_prob": 0.576,
      "end_time": 3.2104,
      "event": "Echolocation",
      "high_freq": 58904,
      "individual": "-1",
      "low_freq": 40937,
      "start_time": 3.2055
    },
    {
      "class": "Myotis daubentonii",
      "class_prob": 0.387,
      "det_prob": 0.622,
      "end_time": 3.2209,
      "event": "Echolocation",
      "high_freq": 62874,
      "individual": "-1",
      "low_freq": 37500,
      "start_time": 3.2165
    },
    {
      "class": "Myotis daubentonii",
      "class_prob": 0.394,
      "det_prob": 0.448,
      "end_time": 3.3104,
      "event": "Echolocation",
      "high_freq": 63724,
      "individual": "-1",
      "low_freq": 35781,
      "start_time": 3.3055
    },
    {
      "class": "Myotis daubentonii",
      "class_prob": 0.45,
      "det_prob": 0.6,
      "end_time": 3.4021,
      "event": "Echolocation",
      "high_freq": 60658,
      "individual": "-1",
      "low_freq": 37500,
      "start_time": 3.3975
    },
    {
      "class": "Myotis daubentonii",
      "class_prob": 0.496,
      "det_prob": 0.556,
      "end_time": 3.414,
      "event": "Echolocation",
      "high_freq": 57407,
      "individual": "-1",
      "low_freq": 41796,
      "start_time": 3.4095
    },
    {
      "class": "Myotis daubentonii",
      "class_prob": 0.517,
      "det_prob": 0.6,
      "end_time": 3.4945,
      "event": "Echolocation",
      "high_freq": 54416,
      "individual": "-1",
      "low_freq": 35781,
      "start_time": 3.4905
    },
    {
      "class": "Myotis daubentonii",
      "class_prob": 0.521,
      "det_prob": 0.594,
      "end_time": 3.5135,
      "event": "Echolocation",
      "high_freq": 56669,
      "individual": "-1",
      "low_freq": 40937,
      "start_time": 3.5085
    },
    {
      "class": "Myotis daubentonii",
      "class_prob": 0.534,
      "det_prob": 0.63,
      "end_time": 3.6126,
      "event": "Echolocation",
      "high_freq": 55112,
      "individual": "-1",
      "low_freq": 41796,
      "start_time": 3.6075
    },
    {
      "class": "Myotis daubentonii",
      "class_prob": 0.494,
      "det_prob": 0.619,
      "end_time": 3.6663,
      "event": "Echolocation",
      "high_freq": 59077,
      "individual": "-1",
      "low_freq": 38359,
      "start_time": 3.6615
    },
    {
      "class": "Myotis daubentonii",
      "class_prob": 0.538,
      "det_prob": 0.641,
      "end_time": 3.7096,
      "event": "Echolocation",
      "high_freq": 58450,
      "individual": "-1",
      "low_freq": 40078,
      "start_time": 3.7045
    },
    {
      "class": "Myotis daubentonii",
      "class_prob": 0.408,
      "det_prob": 0.586,
      "end_time": 3.7538,
      "event": "Echolocation",
      "high_freq": 60538,
      "individual": "-1",
      "low_freq": 40078,
      "start_time": 3.7495
    },
    {
      "class": "Myotis daubentonii",
      "class_prob": 0.436,
      "det_prob": 0.61,
      "end_time": 3.8079,
      "event": "Echolocation",
      "high_freq": 61394,
      "individual": "-1",
      "low_freq": 42656,
      "start_time": 3.8035
    },
    {
      "class": "Myotis daubentonii",
      "class_prob": 0.484,
      "det_prob": 0.585,
      "end_time": 3.8203,
      "event": "Echolocation",
      "high_freq": 61473,
      "individual": "-1",
      "low_freq": 36640,
      "start_time": 3.8155
    },
    {
      "class": "Myotis daubentonii",
      "class_prob": 0.465,
      "det_prob": 0.601,
      "end_time": 3.8699,
      "event": "Echolocation",
      "high_freq": 57437,
      "individual": "-1",
      "low_freq": 38359,
      "start_time": 3.8655
    },
    {
      "class": "Myotis daubentonii",
      "class_prob": 0.44,
      "det_prob": 0.555,
      "end_time": 3.9328,
      "event": "Echolocation",
      "high_freq": 58551,
      "individual": "-1",
      "low_freq": 35781,
      "start_time": 3.9285
    },
    {
      "class": "Myotis daubentonii",
      "class_prob": 0.447,
      "det_prob": 0.596,
      "end_time": 4.0109,
      "event": "Echolocation",
      "high_freq": 54904,
      "individual": "-1",
      "low_freq": 40937,
      "start_time": 4.0065
    },
    {
      "class": "Myotis daubentonii",
      "class_prob": 0.192,
      "det_prob": 0.432,
      "end_time": 4.1011,
      "event": "Echolocation",
      "high_freq": 64476,
      "individual": "-1",
      "low_freq": 30625,
      "start_time": 4.0965
    },
    {
      "class": "Myotis daubentonii",
      "class_prob": 0.315,
      "det_prob": 0.443,
      "end_time": 4.1141,
      "event": "Echolocation",
      "high_freq": 54013,
      "individual": "-1",
      "low_freq": 40937,
      "start_time": 4.1105
    },
    {
      "class": "Myotis mystacinus",
      "class_prob": 0.192,
      "det_prob": 0.465,
      "end_time": 4.2006,
      "event": "Echolocation",
      "high_freq": 62723,
      "individual": "-1",
      "low_freq": 34062,
      "start_time": 4.1965
    },
    {
      "class": "Myotis daubentonii",
      "class_prob": 0.339,
      "det_prob": 0.532,
      "end_time": 4.2139,
      "event": "Echolocation",
      "high_freq": 56133,
      "individual": "-1",
      "low_freq": 40937,
      "start_time": 4.2095
    },
    {
      "class": "Myotis daubentonii",
      "class_prob": 0.232,
      "det_prob": 0.438,
      "end_time": 4.312,
      "event": "Echolocation",
      "high_freq": 55887,
      "individual": "-1",
      "low_freq": 41796,
      "start_time": 4.3085
    },
    {
      "class": "Myotis daubentonii",
      "class_prob": 0.214,
      "det_prob": 0.467,
      "end_time": 4.374,
      "event": "Echolocation",
      "high_freq": 59824,
      "individual": "-1",
      "low_freq": 35781,
      "start_time": 4.3705
    },
    {
      "class": "Myotis daubentonii",
      "class_prob": 0.297,
      "det_prob": 0.503,
      "end_time": 4.558,
      "event": "Echolocation",
      "high_freq": 53032,
      "individual": "-1",
      "low_freq": 36640,
      "start_time": 4.5545
    },
    {
      "class": "Myotis daubentonii",
      "class_prob": 0.23,
      "det_prob": 0.424,
      "end_time": 4.7345,
      "event": "Echolocation",
      "high_freq": 57793,
      "individual": "-1",
      "low_freq": 34921,
      "start_time": 4.7305
    }
  ],
  "class_name": "Myotis daubentonii",
  "duration": 7.1,
  "id": "STADILO_20250402_220825.wav",
  "issues": false,
  "notes": "Automatically generated.",
  "time_exp": 1
}